nonebot_plugin_ottohzys/__init__.py
nonebot_plugin_ottohzys/__main__.py
nonebot_plugin_ottohzys/config.py
nonebot_plugin_ottohzys/migrate.py
nonebot_plugin_ottohzys/pack/__init__.py
nonebot_plugin_ottohzys/pack/audio.py
nonebot_plugin_ottohzys/pack/hzys.py
nonebot_plugin_ottohzys/pack/manager.py
nonebot_plugin_ottohzys/pack/online.py
nonebot_plugin_ottohzys/pack/pack.py
nonebot_plugin_ottohzys/res/chinglish.json
nonebot_plugin_ottohzys-1.0.2.dist-info/METADATA
nonebot_plugin_ottohzys-1.0.2.dist-info/WHEEL
nonebot_plugin_ottohzys-1.0.2.dist-info/RECORD
