Metadata-Version: 2.4
Name: nonebot-plugin-ottohzys
Version: 1.0.2
Summary: otto!
Project-URL: homepage, https://github.com/lgc-NB2Dev/nonebot-plugin-ottohzys
Author-email: LgCookie <lgc2333@126.com>
License: MIT
Requires-Python: <4.0,>=3.10
Requires-Dist: anyio>=4.10.0
Requires-Dist: async-lru>=2.0.5
Requires-Dist: cachetools>=6.1.0
Requires-Dist: cookit[nonebot-alconna,nonebot-localstore,pydantic]>=0.13.0
Requires-Dist: httpx>=0.28.1
Requires-Dist: nonebot-plugin-alconna>=0.59.4
Requires-Dist: nonebot-plugin-localstore>=0.7.4
Requires-Dist: nonebot2>=2.4.3
Requires-Dist: numpy>=2.2.6
Requires-Dist: psola>=0.0.1
Requires-Dist: pypinyin>=0.55.0
Requires-Dist: soundfile>=0.13.1
